filewatch/__init__.py
filewatch/buftok.py
filewatch/tail.py
filewatch/watch.py
pyfilewatch-0.0.3.dist-info/DESCRIPTION.rst
pyfilewatch-0.0.3.dist-info/METADATA
pyfilewatch-0.0.3.dist-info/metadata.json
pyfilewatch-0.0.3.dist-info/RECORD
pyfilewatch-0.0.3.dist-info/top_level.txt
pyfilewatch-0.0.3.dist-info/WHEEL
pyfilewatch-0.0.3.dist-info/zip-safe
