Metadata-Version: 2.0
Name: pyfilewatch
Version: 0.0.3
Summary: Watch files and directories in python. Also supports tailing and glob file patterns.
Home-page: https://github.com/signalfx/pyfilewatch
Author: UNKNOWN
Author-email: UNKNOWN
License: UNKNOWN
Platform: UNKNOWN
Requires-Dist: argparse (>=1.2.1)
